neuralsat/__init__.py
neuralsat/main.py
neuralsat/setting.py
neuralsat/test.py
neuralsat/abstractor/__init__.py
neuralsat/abstractor/abstractor.py
neuralsat/abstractor/params.py
neuralsat/abstractor/utils.py
neuralsat/attacker/attacker.py
neuralsat/attacker/mip_attack.py
neuralsat/attacker/random_attack.py
neuralsat/attacker/pgd_attack/general.py
neuralsat/attacker/pgd_attack/util.py
neuralsat/auto_LiRPA/__init__.py
neuralsat/auto_LiRPA/backward_bound.py
neuralsat/auto_LiRPA/beta_crown.py
neuralsat/auto_LiRPA/bound_general.py
neuralsat/auto_LiRPA/bound_multi_gpu.py
neuralsat/auto_LiRPA/bound_op_map.py
neuralsat/auto_LiRPA/bound_ops.py
neuralsat/auto_LiRPA/bounded_tensor.py
neuralsat/auto_LiRPA/cuda_utils.py
neuralsat/auto_LiRPA/edit_graph.py
neuralsat/auto_LiRPA/eps_scheduler.py
neuralsat/auto_LiRPA/forward_bound.py
neuralsat/auto_LiRPA/interval_bound.py
neuralsat/auto_LiRPA/jacobian.py
neuralsat/auto_LiRPA/linear_bound.py
neuralsat/auto_LiRPA/optimize_graph.py
neuralsat/auto_LiRPA/optimized_bounds.py
neuralsat/auto_LiRPA/parse_graph.py
neuralsat/auto_LiRPA/patches.py
neuralsat/auto_LiRPA/perturbations.py
neuralsat/auto_LiRPA/solver_module.py
neuralsat/auto_LiRPA/utils.py
neuralsat/auto_LiRPA/wrapper.py
neuralsat/auto_LiRPA/operators/__init__.py
neuralsat/auto_LiRPA/operators/activation_base.py
neuralsat/auto_LiRPA/operators/activations.py
neuralsat/auto_LiRPA/operators/add_sub.py
neuralsat/auto_LiRPA/operators/base.py
neuralsat/auto_LiRPA/operators/bivariate.py
neuralsat/auto_LiRPA/operators/clampmult.py
neuralsat/auto_LiRPA/operators/constant.py
neuralsat/auto_LiRPA/operators/convolution.py
neuralsat/auto_LiRPA/operators/dropout.py
neuralsat/auto_LiRPA/operators/dtype.py
neuralsat/auto_LiRPA/operators/gradient_bounds.py
neuralsat/auto_LiRPA/operators/gradient_modules.py
neuralsat/auto_LiRPA/operators/jacobian.py
neuralsat/auto_LiRPA/operators/leaf.py
neuralsat/auto_LiRPA/operators/linear.py
neuralsat/auto_LiRPA/operators/logical.py
neuralsat-0.2.15.dist-info/LICENSE
neuralsat-0.2.15.dist-info/METADATA
neuralsat-0.2.15.dist-info/WHEEL
neuralsat-0.2.15.dist-info/top_level.txt
neuralsat-0.2.15.dist-info/RECORD
