Metadata-Version: 2.1
Name: neuralsat
Version: 0.2.15
Summary: NeuralSAT: A DPLL(T) Framework for Verifying Deep Neural Networks
Author-email: Thanh Le <thanhbok26b@gmail.com>
Project-URL: Homepage, https://github.com/dynaroars/neuralsat/tree/heuristic
Project-URL: Issues, https://github.com/dynaroars/neuralsat/issues
Classifier: Programming Language :: Python :: 3
Classifier: License :: OSI Approved :: MIT License
Classifier: Operating System :: OS Independent
Requires-Python: >=3.8
License-File: LICENSE
